aiotieba_reviewer/__init__.py
aiotieba_reviewer/__version__.py
aiotieba_reviewer/client.py
aiotieba_reviewer/config.py
aiotieba_reviewer/enums.py
aiotieba_reviewer/executor.py
aiotieba_reviewer/imgproc.py
aiotieba_reviewer/perf_stat.py
aiotieba_reviewer/punish.py
aiotieba_reviewer/typing.py
aiotieba_reviewer/database/__init__.py
aiotieba_reviewer/database/postgre.py
aiotieba_reviewer/database/sqlite.py
aiotieba_reviewer/reviewer/__init__.py
aiotieba_reviewer/reviewer/entry.py
aiotieba_reviewer/reviewer/user_checker.py
aiotieba_reviewer/reviewer/comment/__init__.py
aiotieba_reviewer/reviewer/comment/checker.py
aiotieba_reviewer/reviewer/comment/runner.py
aiotieba_reviewer/reviewer/comments/__init__.py
aiotieba_reviewer/reviewer/comments/filter.py
aiotieba_reviewer/reviewer/comments/producer.py
aiotieba_reviewer/reviewer/comments/runner.py
aiotieba_reviewer/reviewer/post/__init__.py
aiotieba_reviewer/reviewer/post/checker.py
aiotieba_reviewer/reviewer/post/runner.py
aiotieba_reviewer/reviewer/posts/__init__.py
aiotieba_reviewer/reviewer/posts/filter.py
aiotieba_reviewer/reviewer/posts/producer.py
aiotieba_reviewer/reviewer/posts/runner.py
aiotieba_reviewer/reviewer/thread/__init__.py
aiotieba_reviewer/reviewer/thread/checker.py
aiotieba_reviewer/reviewer/thread/runner.py
aiotieba_reviewer/reviewer/threads/__init__.py
aiotieba_reviewer/reviewer/threads/filter.py
aiotieba_reviewer/reviewer/threads/producer.py
aiotieba_reviewer/reviewer/threads/runner.py
aiotieba_reviewer-0.7.0.dist-info/METADATA
aiotieba_reviewer-0.7.0.dist-info/WHEEL
aiotieba_reviewer-0.7.0.dist-info/licenses/LICENSE
aiotieba_reviewer-0.7.0.dist-info/RECORD
