Metadata-Version: 2.3
Name: aiotieba-reviewer
Version: 0.7.0
Summary: High Flexibility Anti-spam Framework Based on Aiotieba
Project-URL: Repository, https://github.com/Starry-OvO/aiotieba-reviewer/
Project-URL: Documentation, https://review.aiotieba.cc/
Author-email: Starry-OvO <starry.qvq@gmail.com>
License-File: LICENSE
Keywords: baidu,tieba
Classifier: Development Status :: 4 - Beta
Classifier: Intended Audience :: Developers
Classifier: License :: OSI Approved :: The Unlicense (Unlicense)
Classifier: Operating System :: OS Independent
Classifier: Programming Language :: Python :: 3.8
Classifier: Programming Language :: Python :: 3.9
Classifier: Programming Language :: Python :: 3.10
Classifier: Programming Language :: Python :: 3.11
Classifier: Programming Language :: Python :: 3.12
Classifier: Topic :: Internet :: WWW/HTTP :: Session
Requires-Python: <3.13,>=3.9
Requires-Dist: aiotieba[img,speedup]<5,>=4.4.9
Requires-Dist: asyncpg<0.30,>=0.29
Requires-Dist: tomli<3,>=1.1.0; python_version < '3.11'
